{
  "$schema": "http://json-schema.org/draft-07/schema#",
  "title": "WAN22 Video Generation System Configuration Schema",
  "description": "Configuration schema for WAN22 Video Generation System",
  "type": "object",
  "properties": {
    "system": {
      "type": "object",
      "properties": {
        "name": {
          "type": "string",
          "description": "System name identifier"
        },
        "version": {
          "type": "string",
          "pattern": "^\\d+\\.\\d+\\.\\d+$",
          "description": "System version in semver format"
        },
        "debug": {
          "type": "boolean",
          "default": false,
          "description": "Enable debug mode"
        },
        "log_level": {
          "type": "string",
          "enum": [
            "DEBUG",
            "INFO",
            "WARNING",
            "ERROR",
            "CRITICAL"
          ],
          "default": "INFO",
          "description": "Logging level"
        }
      },
      "required": [
        "name",
        "version"
      ]
    },
    "backend": {
      "type": "object",
      "properties": {
        "api": {
          "type": "object",
          "properties": {
            "host": {
              "type": "string",
              "description": "API server host"
            },
            "port": {
              "type": "integer",
              "minimum": 1,
              "maximum": 65535,
              "description": "API server port"
            },
            "cors_origins": {
              "type": "array",
              "items": {
                "type": "string"
              },
              "description": "Allowed CORS origins"
            },
            "max_request_size": {
              "type": "string",
              "pattern": "^\\d+[KMGT]?B$",
              "description": "Maximum request size"
            },
            "timeout": {
              "type": "integer",
              "minimum": 1,
              "description": "Request timeout in seconds"
            }
          },
          "required": [
            "host",
            "port"
          ]
        }
      }
    }
  }
}